<Properties StartupConfiguration="{D7D51AD0-6B00-4349-9AA0-672C6A956D99}|Default">
  <MonoDevelop.Ide.ItemProperties.GrpcClient PreferredExecutionTarget="MonoDevelop.Default" />
  <MonoDevelop.Ide.Workbench ActiveDocument="GrpcClient/obj/Debug/netcoreapp3.1/Protos/CategoryGrpc.cs">
    <Files>
      <File FileName="GrpcClient/Program.cs" Line="17" Column="66" />
      <File FileName="GrpcClient/Protos/category.proto" Line="39" Column="2" />
      <File FileName="GrpcClient/obj/Debug/netcoreapp3.1/Protos/CategoryGrpc.cs" Line="142" Column="1" />
    </Files>
    <Pads>
      <Pad Id="ProjectPad">
        <State name="__root__">
          <Node name="GrpcClient" expanded="True">
            <Node name="GrpcClient" expanded="True">
              <Node name="Protos" expanded="True" />
              <Node name="Program.cs" selected="True" />
            </Node>
          </Node>
        </State>
      </Pad>
    </Pads>
  </MonoDevelop.Ide.Workbench>
  <MonoDevelop.Ide.DebuggingService.PinnedWatches />
  <MonoDevelop.Ide.Workspace ActiveConfiguration="Debug" />
  <MonoDevelop.Ide.DebuggingService.Breakpoints>
    <BreakpointStore />
  </MonoDevelop.Ide.DebuggingService.Breakpoints>
  <MultiItemStartupConfigurations />
</Properties>